Workbook

Sheet Raw Data
A1: Financial Health Dashboard — Monthly Data (Sample, in $000s)
A2: Note: Sample/illustrative figures for demo purposes. Replace with actual company data.
A4: Month | B4: Revenue ($000s) | C4: COGS ($000s) | D4: Operating Expenses ($000s) | E4: Total Expenses ($000s) | F4: Net Profit ($000s) | G4: Profit Margin (%) | H4: Cumulative Cash Flow ($000s)
A5: Jan | B5: 420 | C5: 210 | D5: 95 | E5: =C5+D5 -> 305 | F5: =B5-E5 -> 115 | G5: =F5/B5 -> 0.27380952 | H5: =F5 -> 115
A6: Feb | B6: 435 | C6: 215 | D6: 98 | E6: =C6+D6 -> 313 | F6: =B6-E6 -> 122 | G6: =F6/B6 -> 0.28045977 | H6: =H5+F6 -> 237
A7: Mar | B7: 460 | C7: 225 | D7: 100 | E7: =C7+D7 -> 325 | F7: =B7-E7 -> 135 | G7: =F7/B7 -> 0.29347826 | H7: =H6+F7 -> 372
A8: Apr | B8: 448 | C8: 222 | D8: 102 | E8: =C8+D8 -> 324 | F8: =B8-E8 -> 124 | G8: =F8/B8 -> 0.27678571 | H8: =H7+F8 -> 496
A9: May | B9: 470 | C9: 230 | D9: 104 | E9: =C9+D9 -> 334 | F9: =B9-E9 -> 136 | G9: =F9/B9 -> 0.2893617 | H9: =H8+F9 -> 632
A10: Jun | B10: 505 | C10: 245 | D10: 108 | E10: =C10+D10 -> 353 | F10: =B10-E10 -> 152 | G10: =F10/B10 -> 0.3009901 | H10: =H9+F10 -> 784
A11: Jul | B11: 512 | C11: 250 | D11: 110 | E11: =C11+D11 -> 360 | F11: =B11-E11 -> 152 | G11: =F11/B11 -> 0.296875 | H11: =H10+F11 -> 936
A12: Aug | B12: 498 | C12: 244 | D12: 112 | E12: =C12+D12 -> 356 | F12: =B12-E12 -> 142 | G12: =F12/B12 -> 0.28514056 | H12: =H11+F12 -> 1078
A13: Sep | B13: 530 | C13: 258 | D13: 115 | E13: =C13+D13 -> 373 | F13: =B13-E13 -> 157 | G13: =F13/B13 -> 0.29622642 | H13: =H12+F13 -> 1235
A14: Oct | B14: 545 | C14: 262 | D14: 118 | E14: =C14+D14 -> 380 | F14: =B14-E14 -> 165 | G14: =F14/B14 -> 0.30275229 | H14: =H13+F14 -> 1400
A15: Nov | B15: 560 | C15: 268 | D15: 120 | E15: =C15+D15 -> 388 | F15: =B15-E15 -> 172 | G15: =F15/B15 -> 0.30714286 | H15: =H14+F15 -> 1572
A16: Dec | B16: 590 | C16: 280 | D16: 125 | E16: =C16+D16 -> 405 | F16: =B16-E16 -> 185 | G16: =F16/B16 -> 0.31355932 | H16: =H15+F16 -> 1757
A18: TOTAL / AVG | B18: =SUM(B5:B16) -> 5973 | C18: =SUM(C5:C16) -> 2909 | D18: =SUM(D5:D16) -> 1307 | E18: =SUM(E5:E16) -> 4216 | F18: =SUM(F5:F16) -> 1757 | G18: =F18/B18 -> 0.29415704 | H18: =H16 -> 1757

Sheet Dashboard
B2: FINANCIAL HEALTH DASHBOARD
B3: Revenue, Expenses, Profitability & Cash Flow Overview — FY (Sample Data)
B5: Total Revenue | E5: Total Expenses | H5: Net Profit | K5: Avg Profit Margin | N5: Ending Cash Position
B6: ='Raw Data'!B18 -> 5973 | E6: ='Raw Data'!E18 -> 4216 | H6: ='Raw Data'!F18 -> 1757 | K6: ='Raw Data'!G18 -> 0.29415704 | N6: ='Raw Data'!H18 -> 1757
B10: Revenue vs Expenses Trend
B29: Monthly Profit Margin (%) | K29: Cumulative Cash Flow ($000s)

Sheet Notes & Assumptions
A1: Notes & Assumptions
A3: 1. All figures are illustrative SAMPLE data (in $000s) built to demonstrate dashboard structure and formulas.
A4: 2. Total Expenses = COGS + Operating Expenses.
A5: 3. Net Profit = Revenue - Total Expenses.
A6: 4. Profit Margin (%) = Net Profit / Revenue.
A7: 5. Cumulative Cash Flow = running total of Net Profit across months (simplified proxy; does not include financing/investing activities).
A8: 6. Replace the blue input cells in the 'Raw Data' sheet with actual company figures to make the dashboard live.
A9: 7. Built as a self-driven portfolio project to demonstrate Excel dashboarding, KPI design, and financial reporting skills.
